{
  "data": [
    {
      "classification": {
        "id": "CRITERION.EXCLUSION.CONVICTIONS.PARTICIPATION_IN_CRIMINAL_ORGANISATION",
        "scheme": "ESPD211"
      },
      "description": "Службова (посадова) особа учасника процедури закупівлі, яка підписала тендерну пропозицію (або уповноважена на підписання договору в разі переговорної процедури закупівлі) або фізична особа, яка є учасником процедури закупівлі, не була засуджена за кримінальне правопорушення, вчинене з корисливих мотивів (зокрема, пов’язане з хабарництвом та відмиванням коштів), судимість з якої знято або погашено у встановленому законом порядку",
      "legislation": [
        {
          "article": "17.1.5",
          "identifier": {
            "id": "922-VIII",
            "legalName": "Закон України \"Про публічні закупівлі\"",
            "uri": "https://zakon.rada.gov.ua/laws/show/922-19"
          },
          "type": "NATIONAL_LEGISLATION",
          "version": "2020-04-19"
        },
        {
          "article": "17.1.6",
          "identifier": {
            "id": "922-VIII",
            "legalName": "Закон України \"Про публічні закупівлі\"",
            "uri": "https://zakon.rada.gov.ua/laws/show/922-19"
          },
          "type": "NATIONAL_LEGISLATION",
          "version": "2020-04-19"
        }
      ],
      "relatesTo": "tenderer",
      "requirementGroups": [
        {
          "description": "Учасник фізична особа підтверджує, що",
          "requirements": [
            {
              "dataType": "boolean",
              "expectedValue": true,
              "id": "e0ea9ac8fc004988a30d40a12a748129",
              "title": "Фізична особа, яка є учасником процедури закупівлі, не була засуджена за кримінальне правопорушення, вчинене з корисливих мотивів (зокрема, пов’язане з хабарництвом та відмиванням коштів), судимість з якої знято або погашено у встановленому законом порядку"
            }
          ]
        },
        {
          "description": "Учасник юридична особа підтверджує, що",
          "requirements": [
            {
              "dataType": "boolean",
              "expectedValue": true,
              "id": "157b7349177b44d8ac90462ba274b2d5",
              "title": "Службова (посадова) особа учасника процедури закупівлі, яка підписала тендерну пропозицію (або уповноважена на підписання договору в разі переговорної процедури закупівлі), не була засуджена за кримінальне правопорушення, вчинене з корисливих мотивів (зокрема, пов’язане з хабарництвом, шахрайством та відмиванням коштів), судимість з якої знято або погашено у встановленому законом порядку"
            }
          ]
        }
      ],
      "source": "tenderer",
      "title": "Вчинення злочинів, учинених з корисливих мотивів"
    },
    {
      "classification": {
        "id": "CRITERION.EXCLUSION.CONVICTIONS.FRAUD",
        "scheme": "ESPD211"
      },
      "description": "Суб'єкт господарювання (учасник) протягом останніх трьох років не притягувався до відповідальності за порушення, передбачене пунктом 4 частини другої статті 6, пунктом 1 статті 50 Закону України \"Про захист економічної конкуренції\", у вигляді вчинення антиконкурентних узгоджених дій, що стосуються спотворення результатів тендерів",
      "legislation": [
        {
          "article": "17.1.4",
          "identifier": {
            "id": "922-VIII",
            "legalName": "Закон України \"Про публічні закупівлі\"",
            "uri": "https://zakon.rada.gov.ua/laws/show/922-19"
          },
          "type": "NATIONAL_LEGISLATION",
          "version": "2020-04-19"
        },
        {
          "article": "6.2.4",
          "identifier": {
            "id": "2210-III",
            "legalName": "Закон України \"Про захист економічної конкуренції\"",
            "uri": "https://zakon.rada.gov.ua/laws/show/2210-14"
          },
          "type": "NATIONAL_LEGISLATION",
          "version": "2020-02-13"
        },
        {
          "article": "50.1",
          "identifier": {
            "id": "2210-III",
            "legalName": "Закон України \"Про захист економічної конкуренції\"",
            "uri": "https://zakon.rada.gov.ua/laws/show/2210-14"
          },
          "type": "NATIONAL_LEGISLATION",
          "version": "2020-02-13"
        }
      ],
      "relatesTo": "tenderer",
      "requirementGroups": [
        {
          "description": "Учасник підтверджує, що",
          "requirements": [
            {
              "dataType": "boolean",
              "expectedValue": true,
              "id": "8a346ee59d7848889553ea5427bfa02b",
              "title": "Суб'єкт господарювання (учасник) протягом останніх трьох років не притягувався до відповідальності за порушення, передбачене пунктом 4 частини другої статті 6, пунктом 1 статті 50 Закону України \"Про захист економічної конкуренції\", у вигляді вчинення антиконкурентних узгоджених дій, що стосуються спотворення результатів тендерів"
            }
          ]
        }
      ],
      "source": "tenderer",
      "title": "Вчинення економічних правопорушень"
    },
    {
      "classification": {
        "id": "CRITERION.EXCLUSION.CONVICTIONS.CORRUPTION",
        "scheme": "ESPD211"
      },
      "description": "Відомості про юридичну особу, яка є учасником процедури закупівлі, не внесено до Єдиного державного реєстру осіб, які вчинили корупційні або пов'язані з корупцією правопорушення. Службову (посадову) особу учасника процедури закупівлі, яку уповноважено учасником представляти його інтереси під час проведення процедури закупівлі, фізичну особу, яка є учасником, не було притягнуто згідно із законом до відповідальності за вчинення корупційного правопорушення або правопорушення, пов'язаного з корупцією",
      "legislation": [
        {
          "article": "17.1.2",
          "identifier": {
            "id": "922-VIII",
            "legalName": "Закон України \"Про публічні закупівлі\"",
            "uri": "https://zakon.rada.gov.ua/laws/show/922-19"
          },
          "type": "NATIONAL_LEGISLATION",
          "version": "2020-04-19"
        },
        {
          "article": "17.1.3",
          "identifier": {
            "id": "922-VIII",
            "legalName": "Закон України \"Про публічні закупівлі\"",
            "uri": "https://zakon.rada.gov.ua/laws/show/922-19"
          },
          "type": "NATIONAL_LEGISLATION",
          "version": "2020-04-19"
        }
      ],
      "relatesTo": "tenderer",
      "requirementGroups": [
        {
          "description": "Учасник підтверджує, що",
          "requirements": [
            {
              "dataType": "boolean",
              "expectedValue": true,
              "id": "b0fa57a6176c43be9581ce8123c1d269",
              "title": "Відомості про юридичну особу, яка є учасником процедури закупівлі, не внесено до Єдиного державного реєстру осіб, які вчинили корупційні або пов'язані з корупцією правопорушення"
            },
            {
              "dataType": "boolean",
              "expectedValue": true,
              "id": "66b9042237c540cfaf8362f67f424eec",
              "title": "Службову (посадову) особу учасника процедури закупівлі, яку уповноважено учасником представляти його інтереси під час проведення процедури закупівлі, фізичну особу, яка є учасником, не було притягнуто згідно із законом до відповідальності за вчинення корупційного правопорушення або правопорушення, пов'язаного з корупцією"
            }
          ]
        }
      ],
      "source": "tenderer",
      "title": "Вчинення корупційних правопорушень"
    },
    {
      "classification": {
        "id": "CRITERION.EXCLUSION.CONVICTIONS.CHILD_LABOUR-HUMAN_TRAFFICKING",
        "scheme": "ESPD211"
      },
      "description": "Службова (посадова) особа учасника процедури закупівлі, яку уповноважено учасником представляти його інтереси під час проведення процедури закупівлі, фізичну особу, яка є учасником, не було притягнуто згідно із законом до відповідальності за вчинення правопорушення, пов'язаного з використанням дитячої праці чи будь-якими формами торгівлі людьми",
      "legislation": [
        {
          "article": "17.1.12",
          "identifier": {
            "id": "922-VIII",
            "legalName": "Закон України \"Про публічні закупівлі\"",
            "uri": "https://zakon.rada.gov.ua/laws/show/922-19"
          },
          "type": "NATIONAL_LEGISLATION",
          "version": "2020-04-19"
        }
      ],
      "relatesTo": "tenderer",
      "requirementGroups": [
        {
          "description": "Учасник підтверджує, що",
          "requirements": [
            {
              "dataType": "boolean",
              "expectedValue": true,
              "id": "cbcced626666410bb7d979d7c7ca1b5e",
              "title": "Службова (посадова) особа учасника процедури закупівлі, яку уповноважено учасником представляти його інтереси під час проведення процедури закупівлі, фізичну особу, яка є учасником, не було притягнуто згідно із законом до відповідальності за вчинення правопорушення, пов'язаного з використанням дитячої праці чи будь-якими формами торгівлі людьми"
            }
          ]
        }
      ],
      "source": "tenderer",
      "title": "Вчинення правопорушень, пов'язаних з використанням дитячої праці чи будь-якими формами торгівлі людьми"
    },
    {
      "classification": {
        "id": "CRITERION.EXCLUSION.CONTRIBUTIONS.PAYMENT_OF_TAXES",
        "scheme": "ESPD211"
      },
      "description": "Учасник процедури закупівлі не має заборгованості зі сплати податків і зборів (обов'язкових платежів)",
      "legislation": [
        {
          "article": "17.1.13",
          "identifier": {
            "id": "922-VIII",
            "legalName": "Закон України \"Про публічні закупівлі\"",
            "uri": "https://zakon.rada.gov.ua/laws/show/922-19"
          },
          "type": "NATIONAL_LEGISLATION",
          "version": "2020-04-19"
        }
      ],
      "relatesTo": "tenderer",
      "requirementGroups": [
        {
          "description": "Учасник підтверджує, що",
          "requirements": [
            {
              "dataType": "boolean",
              "expectedValue": true,
              "id": "d905cbb3823e4c0ebc16c308a3895af5",
              "title": "Він не має заборгованості зі сплати податків і зборів (обов'язкових платежів)"
            }
          ]
        },
        {
          "description": "Учасник підтверджує, що",
          "requirements": [
            {
              "dataType": "boolean",
              "expectedValue": true,
              "id": "1e701d63accc4af189afec14cc3f9713",
              "title": "Він має заборгованість зі сплати податків і зборів (обов'язкових платежів)"
            },
            {
              "dataType": "number",
              "id": "420f009b4a024f6cbae89ea0a8a8caef",
              "title": "Сума існуючої заборгованості"
            },
            {
              "dataType": "string",
              "id": "80f5f98345bc48938d832c92f7cac737",
              "title": "Характер існуючої заборгованості"
            },
            {
              "dataType": "string",
              "id": "aa52037e29b34a5fbf8c143ff74960be",
              "title": "Причина виникнення існуючої заборгованості"
            },
            {
              "dataType": "boolean",
              "expectedValue": true,
              "id": "f67f38ced3154e2793f28b21a51669b3",
              "title": "Учасник здійснив заходи щодо розстрочення і відстрочення такої заборгованості у порядку та на умовах, визначених законодавством країни реєстрації такого учасника"
            }
          ]
        }
      ],
      "source": "tenderer",
      "title": "Заборгованість зі сплати податків і зборів (обов'язкових платежів)"
    },
    {
      "classification": {
        "id": "CRITERION.EXCLUSION.BUSINESS.BANKRUPTCY",
        "scheme": "ESPD211"
      },
      "description": "Учасник процедури закупівлі не визнаний у встановленому законом порядку банкрутом та стосовно нього не відкрита ліквідаційна процедура",
      "legislation": [
        {
          "article": "17.1.8",
          "identifier": {
            "id": "922-VIII",
            "legalName": "Закон України \"Про публічні закупівлі\"",
            "uri": "https://zakon.rada.gov.ua/laws/show/922-19"
          },
          "type": "NATIONAL_LEGISLATION",
          "version": "2020-04-19"
        }
      ],
      "relatesTo": "tenderer",
      "requirementGroups": [
        {
          "description": "Учасник підтверджує, що",
          "requirements": [
            {
              "dataType": "boolean",
              "expectedValue": true,
              "id": "0b19f2e67553435c84a9f1b29195cdf6",
              "title": "Учасник процедури закупівлі не визнаний у встановленому законом порядку банкрутом та стосовно нього не відкрита ліквідаційна процедура"
            }
          ]
        }
      ],
      "source": "tenderer",
      "title": "Порушення справ про банкрутство"
    },
    {
      "classification": {
        "id": "CRITERION.EXCLUSION.MISCONDUCT.MARKET_DISTORTION",
        "scheme": "ESPD211"
      },
      "description": "Тендерна пропозиція подана учасником конкурентної процедури закупівлі або участь у переговорній процедурі бере учасник, який є пов'язаною особою з іншими учасниками процедури закупівлі та/або з уповноваженою особою (особами), та/або з керівником замовника",
      "legislation": [
        {
          "article": "17.1.7",
          "identifier": {
            "id": "922-VIII",
            "legalName": "Закон України \"Про публічні закупівлі\"",
            "uri": "https://zakon.rada.gov.ua/laws/show/922-19"
          },
          "type": "NATIONAL_LEGISLATION",
          "version": "2020-04-19"
        }
      ],
      "relatesTo": "tenderer",
      "requirementGroups": [
        {
          "description": "Замовник підтверджує, що",
          "requirements": [
            {
              "dataType": "boolean",
              "id": "0ce2829010154c58a52998ae7022e81e",
              "title": "Тендерна пропозиція подана учасником конкурентної процедури закупівлі або участь у переговорній процедурі бере учасник, який є пов'язаною особою з іншими учасниками процедури закупівлі та/або з уповноваженою особою (особами), та/або з керівником замовника"
            }
          ]
        }
      ],
      "source": "procuringEntity",
      "title": "Виявлення факту зв'язку учасника з іншими учасниками процедури або замовником"
    },
    {
      "classification": {
        "id": "CRITERION.EXCLUSION.CONFLICT_OF_INTEREST.MISINTERPRETATION",
        "scheme": "ESPD211"
      },
      "description": "Замовник має незаперечні докази того, що учасник процедури закупівлі пропонує, дає або погоджується дати прямо чи опосередковано будь-якій службовій (посадовій) особі замовника, іншого державного органу винагороду в будь-якій формі (пропозиція щодо найму на роботу, цінна річ, послуга тощо) з метою вплинути на прийняття рішення щодо визначення переможця процедури закупівлі або застосування замовником певної процедури закупівлі",
      "legislation": [
        {
          "article": "17.1.1",
          "identifier": {
            "id": "922-VIII",
            "legalName": "Закон України \"Про публічні закупівлі\"",
            "uri": "https://zakon.rada.gov.ua/laws/show/922-19"
          },
          "type": "NATIONAL_LEGISLATION",
          "version": "2020-04-19"
        }
      ],
      "relatesTo": "tenderer",
      "requirementGroups": [
        {
          "description": "Замовник підтверджує, що",
          "requirements": [
            {
              "dataType": "boolean",
              "id": "999fdb9e4e9f4fabb0f7c679f815ef52",
              "title": "Замовник має незаперечні докази того, що учасник процедури закупівлі пропонує, дає або погоджується дати прямо чи опосередковано будь-якій службовій (посадовій) особі замовника, іншого державного органу винагороду в будь-якій формі (пропозиція щодо найму на роботу, цінна річ, послуга тощо) з метою вплинути на прийняття рішення щодо визначення переможця процедури закупівлі або застосування замовником певної процедури закупівлі"
            }
          ]
        }
      ],
      "source": "procuringEntity",
      "title": "Виявлення факту наміру впливу на прийняття рішення замовника"
    },
    {
      "classification": {
        "id": "CRITERION.EXCLUSION.NATIONAL.OTHER",
        "scheme": "ESPD211"
      },
      "description": "У Єдиному державному реєстрі юридичних осіб, фізичних осіб - підприємців та громадських формувань присутня інформація, передбачена пунктом 9 частини другої статті 9 Закону України \"Про державну реєстрацію юридичних осіб, фізичних осіб - підприємців та громадських формувань\" (крім нерезидентів)",
      "legislation": [
        {
          "article": "17.1.9",
          "identifier": {
            "id": "922-VIII",
            "legalName": "Закон України \"Про публічні закупівлі\"",
            "uri": "https://zakon.rada.gov.ua/laws/show/922-19"
          },
          "type": "NATIONAL_LEGISLATION",
          "version": "2020-04-19"
        },
        {
          "article": "9.2.9",
          "identifier": {
            "id": "755-IV",
            "legalName": "Закон України \"Про державну реєстрацію юридичних осіб, фізичних осіб - підприємців та громадських формувань\"",
            "uri": "https://zakon.rada.gov.ua/laws/show/755-15"
          },
          "type": "NATIONAL_LEGISLATION",
          "version": "2020-03-16"
        },
        {
          "article": "17.1.10",
          "identifier": {
            "id": "922-VIII",
            "legalName": "Закон України \"Про публічні закупівлі\"",
            "uri": "https://zakon.rada.gov.ua/laws/show/922-19"
          },
          "type": "NATIONAL_LEGISLATION",
          "version": "2020-04-19"
        },
        {
          "article": "17.1.11",
          "identifier": {
            "id": "922-VIII",
            "legalName": "Закон України \"Про публічні закупівлі\"",
            "uri": "https://zakon.rada.gov.ua/laws/show/922-19"
          },
          "type": "NATIONAL_LEGISLATION",
          "version": "2020-04-19"
        },
        {
          "identifier": {
            "id": "1644-VII",
            "legalName": "Закон України \"Про санкції\"",
            "uri": "https://zakon.rada.gov.ua/laws/show/1644-18"
          },
          "type": "NATIONAL_LEGISLATION",
          "version": "2020-04-19"
        }
      ],
      "relatesTo": "tenderer",
      "requirementGroups": [
        {
          "description": "Учасник підтверджує, що",
          "requirements": [
            {
              "dataType": "boolean",
              "expectedValue": true,
              "id": "c4124372919f473dad63dfb133a5aa26",
              "title": "У Єдиному державному реєстрі юридичних осіб, фізичних осіб - підприємців та громадських формувань присутня інформація, передбачена пунктом 9 частини другої статті 9 Закону України \"Про державну реєстрацію юридичних осіб, фізичних осіб - підприємців та громадських формувань\" (крім нерезидентів)"
            },
            {
              "dataType": "boolean",
              "expectedValue": true,
              "id": "9dcd3744ea5743f1b7063dea68a30f0b",
              "title": "Юридична особа, яка є учасником процедури закупівлі (крім нерезидентів), має антикорупційну програму чи уповноваженого з реалізації антикорупційної програми, якщо вартість закупівлі товару (товарів), послуги (послуг) або робіт дорівнює чи перевищує 20 мільйонів гривень (у тому числі за лотом)"
            },
            {
              "dataType": "boolean",
              "expectedValue": true,
              "id": "72d324aaddf74f42896dcd1917b34238",
              "title": "Учасник процедури закупівлі не є особою, до якої застосовано санкцію у вигляді заборони на здійснення у неї публічних закупівель товарів, робіт і послуг згідно із Законом України \"Про санкції\""
            }
          ]
        }
      ],
      "source": "tenderer",
      "title": "Наявність інших підстав для відмови в участі у процедурі закупівлі"
    },
    {
      "classification": {
        "id": "CRITERION.OTHER.BID.LANGUAGE",
        "scheme": "ESPD211"
      },
      "legislation": [
        {
          "identifier": {
            "id": "922-VIII",
            "legalName": "Закон України \"Про публічні закупівлі\"",
            "uri": "https://zakon.rada.gov.ua/laws/show/922-19"
          },
          "type": "NATIONAL_LEGISLATION",
          "version": "2020-04-19"
        }
      ],
      "relatesTo": "tender",
      "requirementGroups": [
        {
          "description": "Учасник підтверджує, що",
          "requirements": [
            {
              "dataType": "boolean",
              "expectedValue": true,
              "id": "bed94028e8d244c19c4e543b9df9da91",
              "title": "Мова тендерної пропозиції українська"
            }
          ]
        }
      ],
      "source": "tenderer",
      "title": "Мова (мови), якою (якими) повинні готуватися тендерні пропозиції"
    },
    {
      "classification": {
        "id": "CRITERION.OTHER.BID.GUARANTEE",
        "scheme": "ESPD211"
      },
      "legislation": [
        {
          "identifier": {
            "id": "922-VIII",
            "legalName": "Закон України \"Про публічні закупівлі\"",
            "uri": "https://zakon.rada.gov.ua/laws/show/922-19"
          },
          "type": "NATIONAL_LEGISLATION",
          "version": "2020-04-19"
        }
      ],
      "relatedItem": "dd22c9c085f64e019f943999b5b41fe5",
      "relatesTo": "lot",
      "requirementGroups": [
        {
          "description": "Учасник підтверджує, що",
          "requirements": [
            {
              "dataType": "boolean",
              "expectedValue": true,
              "id": "4312983af6e04b0bbf47c55f9a99ca20",
              "title": "Вид та умови надання забезпечення тендерних пропозицій"
            }
          ]
        }
      ],
      "source": "tenderer",
      "title": "Забезпечення тендерних пропозицій"
    },
    {
      "classification": {
        "id": "CRITERION.OTHER.CONTRACT.GUARANTEE",
        "scheme": "ESPD211"
      },
      "legislation": [
        {
          "identifier": {
            "id": "922-VIII",
            "legalName": "Закон України \"Про публічні закупівлі\"",
            "uri": "https://zakon.rada.gov.ua/laws/show/922-19"
          },
          "type": "NATIONAL_LEGISLATION",
          "version": "2020-04-19"
        }
      ],
      "relatedItem": "dd22c9c085f64e019f943999b5b41fe5",
      "relatesTo": "lot",
      "requirementGroups": [
        {
          "description": "Учасник підтверджує, що",
          "requirements": [
            {
              "dataType": "boolean",
              "expectedValue": true,
              "id": "8c28438b1a034a939154c320a67dd9fa",
              "title": "Розмір та умови надання забезпечення виконання договору про закупівлю"
            }
          ]
        }
      ],
      "source": "winner",
      "title": "Забезпечення виконання договору"
    },
    {
      "classification": {
        "id": "CRITERION.OTHER.BID.GUARANTEE",
        "scheme": "ESPD211"
      },
      "legislation": [
        {
          "identifier": {
            "id": "922-VIII",
            "legalName": "Закон України \"Про публічні закупівлі\"",
            "uri": "https://zakon.rada.gov.ua/laws/show/922-19"
          },
          "type": "NATIONAL_LEGISLATION",
          "version": "2020-04-19"
        }
      ],
      "relatedItem": "9d4fc4783ebb4a99b10cc9a2f7d7552f",
      "relatesTo": "lot",
      "requirementGroups": [
        {
          "description": "Учасник підтверджує, що",
          "requirements": [
            {
              "dataType": "boolean",
              "expectedValue": true,
              "id": "bbfe1e4a371d40718a8367e67af87ff7",
              "title": "Вид та умови надання забезпечення тендерних пропозицій"
            }
          ]
        }
      ],
      "source": "tenderer",
      "title": "Забезпечення тендерних пропозицій"
    },
    {
      "classification": {
        "id": "CRITERION.OTHER.CONTRACT.GUARANTEE",
        "scheme": "ESPD211"
      },
      "legislation": [
        {
          "identifier": {
            "id": "922-VIII",
            "legalName": "Закон України \"Про публічні закупівлі\"",
            "uri": "https://zakon.rada.gov.ua/laws/show/922-19"
          },
          "type": "NATIONAL_LEGISLATION",
          "version": "2020-04-19"
        }
      ],
      "relatedItem": "9d4fc4783ebb4a99b10cc9a2f7d7552f",
      "relatesTo": "lot",
      "requirementGroups": [
        {
          "description": "Учасник підтверджує, що",
          "requirements": [
            {
              "dataType": "boolean",
              "expectedValue": true,
              "id": "8152afbace4e4043a42de30acdeaf931",
              "title": "Розмір та умови надання забезпечення виконання договору про закупівлю"
            }
          ]
        }
      ],
      "source": "winner",
      "title": "Забезпечення виконання договору"
    },
    {
      "classification": {
        "id": "CRITERION.SELECTION.TECHNICAL_PROFESSIONAL_ABILITY.TECHNICAL.EQUIPMENT",
        "scheme": "ESPD211"
      },
      "description": "Наявність в учасника процедури закупівлі обладнання, матеріально-технічної бази та технологій;",
      "legislation": [
        {
          "article": "16.2.1",
          "identifier": {
            "id": "922-VIII",
            "legalName": "Закон України \"Про публічні закупівлі\"",
            "uri": "https://zakon.rada.gov.ua/laws/show/922-19"
          },
          "type": "NATIONAL_LEGISLATION",
          "version": "2021-12-16"
        }
      ],
      "relatesTo": "tenderer",
      "requirementGroups": [
        {
          "description": "Підтверджується, що",
          "requirements": [
            {
              "dataType": "boolean",
              "expectedValue": true,
              "id": "75b4c78d36a149d7aaa7bdfbda2fcee1",
              "title": "Lorem ipsum dolor sit amet, consectetur adipiscing elit"
            }
          ]
        }
      ],
      "source": "tenderer",
      "title": "Наявність обладнання, матеріально-технічної бази та технологій"
    },
    {
      "classification": {
        "id": "CRITERION.SELECTION.TECHNICAL_PROFESSIONAL_ABILITY.TECHNICAL.STAFF_FOR_CARRYING_SCOPE",
        "scheme": "ESPD211"
      },
      "description": "Наявність в учасника процедури закупівлі працівників відповідної кваліфікації, які мають необхідні знання та досвід;",
      "legislation": [
        {
          "article": "16.2.2",
          "identifier": {
            "id": "922-VIII",
            "legalName": "Закон України \"Про публічні закупівлі\"",
            "uri": "https://zakon.rada.gov.ua/laws/show/922-19"
          },
          "type": "NATIONAL_LEGISLATION",
          "version": "2021-12-16"
        }
      ],
      "relatesTo": "tenderer",
      "requirementGroups": [
        {
          "description": "Підтверджується, що",
          "requirements": [
            {
              "dataType": "boolean",
              "expectedValue": true,
              "id": "c09762d3461d4d3789f84bcbb36ea2ae",
              "title": "Lorem ipsum dolor sit amet, consectetur adipiscing elit"
            }
          ]
        }
      ],
      "source": "tenderer",
      "title": "Наявність працівників відповідної кваліфікації"
    },
    {
      "classification": {
        "id": "CRITERION.SELECTION.TECHNICAL_PROFESSIONAL_ABILITY.REFERENCES.WORKS_PERFORMANCE",
        "scheme": "ESPD211"
      },
      "description": "Наявність документально підтвердженого досвіду виконання аналогічного (аналогічних) за предметом закупівлі договору (договорів);",
      "legislation": [
        {
          "article": "16.2.3",
          "identifier": {
            "id": "922-VIII",
            "legalName": "Закон України \"Про публічні закупівлі\"",
            "uri": "https://zakon.rada.gov.ua/laws/show/922-19"
          },
          "type": "NATIONAL_LEGISLATION",
          "version": "2021-12-16"
        }
      ],
      "relatesTo": "tenderer",
      "requirementGroups": [
        {
          "description": "Підтверджується, що",
          "requirements": [
            {
              "dataType": "boolean",
              "expectedValue": true,
              "id": "83c15d8f026342808757a29f25466fb0",
              "title": "Lorem ipsum dolor sit amet, consectetur adipiscing elit"
            }
          ]
        }
      ],
      "source": "tenderer",
      "title": "Наявність досвіду виконання аналогічного (аналогічних) договору (договорів)"
    },
    {
      "classification": {
        "id": "CRITERION.SELECTION.ECONOMIC_FINANCIAL_STANDING",
        "scheme": "ESPD211"
      },
      "description": "Наявність фінансової спроможності, яка підтверджується фінансовою звітністю.",
      "legislation": [
        {
          "article": "16.2.4",
          "identifier": {
            "id": "922-VIII",
            "legalName": "Закон України \"Про публічні закупівлі\"",
            "uri": "https://zakon.rada.gov.ua/laws/show/922-19"
          },
          "type": "NATIONAL_LEGISLATION",
          "version": "2021-12-16"
        }
      ],
      "relatesTo": "tenderer",
      "requirementGroups": [
        {
          "description": "Підтверджується, що",
          "requirements": [
            {
              "dataType": "boolean",
              "expectedValue": true,
              "id": "b7a9c4ab41dd4d2f97928e6748a6ea7b",
              "title": "Lorem ipsum dolor sit amet, consectetur adipiscing elit"
            }
          ]
        }
      ],
      "source": "tenderer",
      "title": "Наявність фінансової спроможності"
    }
  ]
}