{
  "data": {
    "lotValues": [
      {
        "relatedLot": "ddb35dd0e9904726aafd18baed24863a",
        "value": {
          "amount": 2.4
        }
      }
    ],
    "parameters": [
      {
        "code": "OCDS-123454-AIR-INTAKE",
        "value": 0.1
      }
    ],
    "status": "draft",
    "tenderers": [
      {
        "address": {
          "countryName": "Україна",
          "locality": "м. Львів",
          "postalCode": "79013",
          "region": "Львівська область",
          "streetAddress": "вул. Тестова 34"
        },
        "contactPoint": {
          "email": "business@example.com",
          "name": "Контактенко Контакт Контактович",
          "telephone": "+380111111111"
        },
        "identifier": {
          "id": "00137224",
          "scheme": "UA-EDR",
          "uri": "http://factory.example.com"
        },
        "name": "Тестове державне комунальне підприємство",
        "scale": "micro"
      }
    ],
    "documents": [
      {
        "title": "bid_document_file.txt"
      },
      {
        "title": "bid_confidential_document_file.txt",
        "confidentiality": "buyerOnly",
        "confidentialityRationale": "Доступ до цього документу має бути обмежений лише для замовника"
      }
    ],
    "eligibilityDocuments": [
      {
        "title": "bid_eligibility_document_file.txt"
      }
    ],
    "financialDocuments": [
      {
        "title": "bid_financial_document_file.txt"
      }
    ],
    "qualificationDocuments": [
      {
        "title": "bid_qualification_document_file.txt"
      }
    ]
  }
}
